fpga/vthacks.sv
module fpga_vthacks(
    input logic clock,
    input logic [31:0] button_array,
    output logic uart_tx
);

    logic divided_clock64;
    logic is_uart_send_finished;
    logic [31:0] button_array_buffer;
    logic initiate_send_signal_uart;
    
    
    clock_divider_64 clock_divider(.clock_in(clock), .clock_out(divided_clock64));


    // send values from button array to uart -------------------------------------------------------
    assign initiate_send_signal_uart = 1;
    register_to_uart register_to_uart(
        .clock(divided_clock64), .initiate_send_signal_uart(initiate_send_signal_uart), 
        .data_to_send(button_array), .uart_tx(uart_tx), 
        .is_uart_send_finished(is_uart_send_finished)
    );

    // always @(posedge is_uart_send_finished) begin
    //     button_array_buffer <= button_array;
    // end

    // ---------------------------------------------------------------------------------------------


endmodule



module clock_divider_64(
    input logic clock_in,
    output logic clock_out
);
    logic [8:0] count;

    initial begin
        count <= 0;
        clock_out = 0;
    end

    always @(posedge clock_in) begin
        
        
        if (count == 1 - 1) begin
            count <= 0;
            clock_out <= ~clock_out; 
        end 
        
        else begin
            count <= count + 1;
        end
    
    end


endmodule



module register_to_uart (
    input logic clock,
    input logic initiate_send_signal_uart,
    input logic [31:0] data_to_send,
    output logic uart_tx,
    output logic is_uart_send_finished
);
    logic [3:0] bit_counter;
    logic [1:0] packet_counter;

    initial begin
        bit_counter <= 0;
        packet_counter <= 0;
        uart_tx <= 1;
        is_uart_send_finished <= 1;
    end

    always @(posedge clock) begin
        
        // write the stop bit
        if (bit_counter == 4'b1001) begin
            uart_tx <= 1;
            bit_counter <= 0;

            if (packet_counter == 2'b11) begin
                packet_counter <= 0;
            end

            else begin
                packet_counter <= packet_counter + 1;
            end
        end

        // normal operation
        else if (bit_counter != 0) begin
            bit_counter <= bit_counter + 1;
            uart_tx <= data_to_send[packet_counter * 8 + (bit_counter-1)];
        end

        // initiate the state machine
        else if (initiate_send_signal_uart && bit_counter == 0) begin
            bit_counter++;
            uart_tx <= 0; 
            is_uart_send_finished <= 0;
        end
    end

endmodule

fpga/vthacks_test_bench.sv
`timescale 1ns / 1ps
`default_nettype wire

module vthacks_test_bench();
    logic clock;
    logic [31:0] button_array;
    logic uart_tx;

    fpga_vthacks fpga_vthacks(.clock(clock), .button_array(button_array), .uart_tx(uart_tx));


    initial begin
        $dumpfile("build/vthacks_test_bench.vcd"); //file to store value change dump (vcd)
        $dumpvars(0, vthacks_test_bench); //store everything at the current level and below


        clock = 0;
        button_array = 32'b00000000000000000000000000000000;

        # 160

        button_array = 32'b10000000000000000000000000000000;

        # 160

        button_array = 32'b11000000000000000000000000000000;

        # 160 

        button_array = 32'b00000000000000000000000000000111;

        # 160

        button_array = 32'b00000000000000000000000000000000;

        # 160

        button_array = 32'b10000000000000000000000000000000;

        # 160 

        button_array = 32'b11000000000000000000000000000000;

        # 160 

        button_array = 32'b00000000000000000000000000000111;

        $display("Finishing Sim");
        $finish;
    end


    always begin
        #1 clock = !clock;
    end
endmodule

fpga/build/vthacks_test_bench.vcd
$date
	Sun Sep 28 15:28:49 2025
$end
$version
	Icarus Verilog
$end
$timescale
	1ps
$end
$scope module vthacks_test_bench $end
$var wire 1 ! uart_tx $end
$var reg 32 " button_array [31:0] $end
$var reg 1 # clock $end
$scope module fpga_vthacks $end
$var wire 32 $ button_array [31:0] $end
$var wire 1 # clock $end
$var wire 1 % initiate_send_signal_uart $end
$var wire 1 ! uart_tx $end
$var wire 1 & is_uart_send_finished $end
$var wire 1 ' divided_clock64 $end
$scope module clock_divider $end
$var wire 1 # clock_in $end
$var reg 1 ' clock_out $end
$var reg 9 ( count [8:0] $end
$upscope $end
$scope module register_to_uart $end
$var wire 1 ' clock $end
$var wire 32 ) data_to_send [31:0] $end
$var wire 1 % initiate_send_signal_uart $end
$var reg 4 * bit_counter [3:0] $end
$var reg 1 & is_uart_send_finished $end
$var reg 2 + packet_counter [1:0] $end
$var reg 1 ! uart_tx $end
$upscope $end
$upscope $end
$upscope $end
$enddefinitions $end
$comment Show the parameter values. $end
$dumpall
$end
#0
$dumpvars
b0 +
b0 *
b0 )
b0 (
0'
1&
1%
b0 $
0#
b0 "
1!
$end
#1000
0&
0!
b1 *
1'
1#
#2000
0#
#3000
0'
1#
#4000
0#
#5000
b10 *
1'
1#
#6000
0#
#7000
0'
1#
#8000
0#
#9000
b11 *
1'
1#
#10000
0#
#11000
0'
1#
#12000
0#
#13000
b100 *
1'
1#
#14000
0#
#15000
0'
1#
#16000
0#
#17000
b101 *
1'
1#
#18000
0#
#19000
0'
1#
#20000
0#
#21000
b110 *
1'
1#
#22000
0#
#23000
0'
1#
#24000
0#
#25000
b111 *
1'
1#
#26000
0#
#27000
0'
1#
#28000
0#
#29000
b1000 *
1'
1#
#30000
0#
#31000
0'
1#
#32000
0#
#33000
b1001 *
1'
1#
#34000
0#
#35000
0'
1#
#36000
0#
#37000
b1 +
b0 *
1!
1'
1#
#38000
0#
#39000
0'
1#
#40000
0#
#41000
0!
b1 *
1'
1#
#42000
0#
#43000
0'
1#
#44000
0#
#45000
b10 *
1'
1#
#46000
0#
#47000
0'
1#
#48000
0#
#49000
b11 *
1'
1#
#50000
0#
#51000
0'
1#
#52000
0#
#53000
b100 *
1'
1#
#54000
0#
#55000
0'
1#
#56000
0#
#57000
b101 *
1'
1#
#58000
0#
#59000
0'
1#
#60000
0#
#61000
b110 *
1'
1#
#62000
0#
#63000
0'
1#
#64000
0#
#65000
b111 *
1'
1#
#66000
0#
#67000
0'
1#
#68000
0#
#69000
b1000 *
1'
1#
#70000
0#
#71000
0'
1#
#72000
0#
#73000
b1001 *
1'
1#
#74000
0#
#75000
0'
1#
#76000
0#
#77000
b10 +
b0 *
1!
1'
1#
#78000
0#
#79000
0'
1#
#80000
0#
#81000
0!
b1 *
1'
1#
#82000
0#
#83000
0'
1#
#84000
0#
#85000
b10 *
1'
1#
#86000
0#
#87000
0'
1#
#88000
0#
#89000
b11 *
1'
1#
#90000
0#
#91000
0'
1#
#92000
0#
#93000
b100 *
1'
1#
#94000
0#
#95000
0'
1#
#96000
0#
#97000
b101 *
1'
1#
#98000
0#
#99000
0'
1#
#100000
0#
#101000
b110 *
1'
1#
#102000
0#
#103000
0'
1#
#104000
0#
#105000
b111 *
1'
1#
#106000
0#
#107000
0'
1#
#108000
0#
#109000
b1000 *
1'
1#
#110000
0#
#111000
0'
1#
#112000
0#
#113000
b1001 *
1'
1#
#114000
0#
#115000
0'
1#
#116000
0#
#117000
b11 +
b0 *
1!
1'
1#
#118000
0#
#119000
0'
1#
#120000
0#
#121000
0!
b1 *
1'
1#
#122000
0#
#123000
0'
1#
#124000
0#
#125000
b10 *
1'
1#
#126000
0#
#127000
0'
1#
#128000
0#
#129000
b11 *
1'
1#
#130000
0#
#131000
0'
1#
#132000
0#
#133000
b100 *
1'
1#
#134000
0#
#135000
0'
1#
#136000
0#
#137000
b101 *
1'
1#
#138000
0#
#139000
0'
1#
#140000
0#
#141000
b110 *
1'
1#
#142000
0#
#143000
0'
1#
#144000
0#
#145000
b111 *
1'
1#
#146000
0#
#147000
0'
1#
#148000
0#
#149000
b1000 *
1'
1#
#150000
0#
#151000
0'
1#
#152000
0#
#153000
b1001 *
1'
1#
#154000
0#
#155000
0'
1#
#156000
0#
#157000
b0 +
b0 *
1!
1'
1#
#158000
0#
#159000
0'
1#
#160000
0#
b10000000000000000000000000000000 "
b10000000000000000000000000000000 $
b10000000000000000000000000000000 )
#161000
0!
b1 *
1'
1#
#162000
0#
#163000
0'
1#
#164000
0#
#165000
b10 *
1'
1#
#166000
0#
#167000
0'
1#
#168000
0#
#169000
b11 *
1'
1#
#170000
0#
#171000
0'
1#
#172000
0#
#173000
b100 *
1'
1#
#174000
0#
#175000
0'
1#
#176000
0#
#177000
b101 *
1'
1#
#178000
0#
#179000
0'
1#
#180000
0#
#181000
b110 *
1'
1#
#182000
0#
#183000
0'
1#
#184000
0#
#185000
b111 *
1'
1#
#186000
0#
#187000
0'
1#
#188000
0#
#189000
b1000 *
1'
1#
#190000
0#
#191000
0'
1#
#192000
0#
#193000
b1001 *
1'
1#
#194000
0#
#195000
0'
1#
#196000
0#
#197000
b1 +
b0 *
1!
1'
1#
#198000
0#
#199000
0'
1#
#200000
0#
#201000
0!
b1 *
1'
1#
#202000
0#
#203000
0'
1#
#204000
0#
#205000
b10 *
1'
1#
#206000
0#
#207000
0'
1#
#208000
0#
#209000
b11 *
1'
1#
#210000
0#
#211000
0'
1#
#212000
0#
#213000
b100 *
1'
1#
#214000
0#
#215000
0'
1#
#216000
0#
#217000
b101 *
1'
1#
#218000
0#
#219000
0'
1#
#220000
0#
#221000
b110 *
1'
1#
#222000
0#
#223000
0'
1#
#224000
0#
#225000
b111 *
1'
1#
#226000
0#
#227000
0'
1#
#228000
0#
#229000
b1000 *
1'
1#
#230000
0#
#231000
0'
1#
#232000
0#
#233000
b1001 *
1'
1#
#234000
0#
#235000
0'
1#
#236000
0#
#237000
b10 +
b0 *
1!
1'
1#
#238000
0#
#239000
0'
1#
#240000
0#
#241000
0!
b1 *
1'
1#
#242000
0#
#243000
0'
1#
#244000
0#
#245000
b10 *
1'
1#
#246000
0#
#247000
0'
1#
#248000
0#
#249000
b11 *
1'
1#
#250000
0#
#251000
0'
1#
#252000
0#
#253000
b100 *
1'
1#
#254000
0#
#255000
0'
1#
#256000
0#
#257000
b101 *
1'
1#
#258000
0#
#259000
0'
1#
#260000
0#
#261000
b110 *
1'
1#
#262000
0#
#263000
0'
1#
#264000
0#
#265000
b111 *
1'
1#
#266000
0#
#267000
0'
1#
#268000
0#
#269000
b1000 *
1'
1#
#270000
0#
#271000
0'
1#
#272000
0#
#273000
b1001 *
1'
1#
#274000
0#
#275000
0'
1#
#276000
0#
#277000
b11 +
b0 *
1!
1'
1#
#278000
0#
#279000
0'
1#
#280000
0#
#281000
0!
b1 *
1'
1#
#282000
0#
#283000
0'
1#
#284000
0#
#285000
b10 *
1'
1#
#286000
0#
#287000
0'
1#
#288000
0#
#289000
b11 *
1'
1#
#290000
0#
#291000
0'
1#
#292000
0#
#293000
b100 *
1'
1#
#294000
0#
#295000
0'
1#
#296000
0#
#297000
b101 *
1'
1#
#298000
0#
#299000
0'
1#
#300000
0#
#301000
b110 *
1'
1#
#302000
0#
#303000
0'
1#
#304000
0#
#305000
b111 *
1'
1#
#306000
0#
#307000
0'
1#
#308000
0#
#309000
b1000 *
1'
1#
#310000
0#
#311000
0'
1#
#312000
0#
#313000
1!
b1001 *
1'
1#
#314000
0#
#315000
0'
1#
#316000
0#
#317000
b0 +
b0 *
1'
1#
#318000
0#
#319000
0'
1#
#320000
0#
b11000000000000000000000000000000 "
b11000000000000000000000000000000 $
b11000000000000000000000000000000 )
#321000
0!
b1 *
1'
1#
#322000
0#
#323000
0'
1#
#324000
0#
#325000
b10 *
1'
1#
#326000
0#
#327000
0'
1#
#328000
0#
#329000
b11 *
1'
1#
#330000
0#
#331000
0'
1#
#332000
0#
#333000
b100 *
1'
1#
#334000
0#
#335000
0'
1#
#336000
0#
#337000
b101 *
1'
1#
#338000
0#
#339000
0'
1#
#340000
0#
#341000
b110 *
1'
1#
#342000
0#
#343000
0'
1#
#344000
0#
#345000
b111 *
1'
1#
#346000
0#
#347000
0'
1#
#348000
0#
#349000
b1000 *
1'
1#
#350000
0#
#351000
0'
1#
#352000
0#
#353000
b1001 *
1'
1#
#354000
0#
#355000
0'
1#
#356000
0#
#357000
b1 +
b0 *
1!
1'
1#
#358000
0#
#359000
0'
1#
#360000
0#
#361000
0!
b1 *
1'
1#
#362000
0#
#363000
0'
1#
#364000
0#
#365000
b10 *
1'
1#
#366000
0#
#367000
0'
1#
#368000
0#
#369000
b11 *
1'
1#
#370000
0#
#371000
0'
1#
#372000
0#
#373000
b100 *
1'
1#
#374000
0#
#375000
0'
1#
#376000
0#
#377000
b101 *
1'
1#
#378000
0#
#379000
0'
1#
#380000
0#
#381000
b110 *
1'
1#
#382000
0#
#383000
0'
1#
#384000
0#
#385000
b111 *
1'
1#
#386000
0#
#387000
0'
1#
#388000
0#
#389000
b1000 *
1'
1#
#390000
0#
#391000
0'
1#
#392000
0#
#393000
b1001 *
1'
1#
#394000
0#
#395000
0'
1#
#396000
0#
#397000
b10 +
b0 *
1!
1'
1#
#398000
0#
#399000
0'
1#
#400000
0#
#401000
0!
b1 *
1'
1#
#402000
0#
#403000
0'
1#
#404000
0#
#405000
b10 *
1'
1#
#406000
0#
#407000
0'
1#
#408000
0#
#409000
b11 *
1'
1#
#410000
0#
#411000
0'
1#
#412000
0#
#413000
b100 *
1'
1#
#414000
0#
#415000
0'
1#
#416000
0#
#417000
b101 *
1'
1#
#418000
0#
#419000
0'
1#
#420000
0#
#421000
b110 *
1'
1#
#422000
0#
#423000
0'
1#
#424000
0#
#425000
b111 *
1'
1#
#426000
0#
#427000
0'
1#
#428000
0#
#429000
b1000 *
1'
1#
#430000
0#
#431000
0'
1#
#432000
0#
#433000
b1001 *
1'
1#
#434000
0#
#435000
0'
1#
#436000
0#
#437000
b11 +
b0 *
1!
1'
1#
#438000
0#
#439000
0'
1#
#440000
0#
#441000
0!
b1 *
1'
1#
#442000
0#
#443000
0'
1#
#444000
0#
#445000
b10 *
1'
1#
#446000
0#
#447000
0'
1#
#448000
0#
#449000
b11 *
1'
1#
#450000
0#
#451000
0'
1#
#452000
0#
#453000
b100 *
1'
1#
#454000
0#
#455000
0'
1#
#456000
0#
#457000
b101 *
1'
1#
#458000
0#
#459000
0'
1#
#460000
0#
#461000
b110 *
1'
1#
#462000
0#
#463000
0'
1#
#464000
0#
#465000
b111 *
1'
1#
#466000
0#
#467000
0'
1#
#468000
0#
#469000
1!
b1000 *
1'
1#
#470000
0#
#471000
0'
1#
#472000
0#
#473000
b1001 *
1'
1#
#474000
0#
#475000
0'
1#
#476000
0#
#477000
b0 +
b0 *
1'
1#
#478000
0#
#479000
0'
1#
#480000
0#
b111 "
b111 $
b111 )
#481000
0!
b1 *
1'
1#
#482000
0#
#483000
0'
1#
#484000
0#
#485000
1!
b10 *
1'
1#
#486000
0#
#487000
0'
1#
#488000
0#
#489000
b11 *
1'
1#
#490000
0#
#491000
0'
1#
#492000
0#
#493000
b100 *
1'
1#
#494000
0#
#495000
0'
1#
#496000
0#
#497000
0!
b101 *
1'
1#
#498000
0#
#499000
0'
1#
#500000
0#
#501000
b110 *
1'
1#
#502000
0#
#503000
0'
1#
#504000
0#
#505000
b111 *
1'
1#
#506000
0#
#507000
0'
1#
#508000
0#
#509000
b1000 *
1'
1#
#510000
0#
#511000
0'
1#
#512000
0#
#513000
b1001 *
1'
1#
#514000
0#
#515000
0'
1#
#516000
0#
#517000
b1 +
b0 *
1!
1'
1#
#518000
0#
#519000
0'
1#
#520000
0#
#521000
0!
b1 *
1'
1#
#522000
0#
#523000
0'
1#
#524000
0#
#525000
b10 *
1'
1#
#526000
0#
#527000
0'
1#
#528000
0#
#529000
b11 *
1'
1#
#530000
0#
#531000
0'
1#
#532000
0#
#533000
b100 *
1'
1#
#534000
0#
#535000
0'
1#
#536000
0#
#537000
b101 *
1'
1#
#538000
0#
#539000
0'
1#
#540000
0#
#541000
b110 *
1'
1#
#542000
0#
#543000
0'
1#
#544000
0#
#545000
b111 *
1'
1#
#546000
0#
#547000
0'
1#
#548000
0#
#549000
b1000 *
1'
1#
#550000
0#
#551000
0'
1#
#552000
0#
#553000
b1001 *
1'
1#
#554000
0#
#555000
0'
1#
#556000
0#
#557000
b10 +
b0 *
1!
1'
1#
#558000
0#
#559000
0'
1#
#560000
0#
#561000
0!
b1 *
1'
1#
#562000
0#
#563000
0'
1#
#564000
0#
#565000
b10 *
1'
1#
#566000
0#
#567000
0'
1#
#568000
0#
#569000
b11 *
1'
1#
#570000
0#
#571000
0'
1#
#572000
0#
#573000
b100 *
1'
1#
#574000
0#
#575000
0'
1#
#576000
0#
#577000
b101 *
1'
1#
#578000
0#
#579000
0'
1#
#580000
0#
#581000
b110 *
1'
1#
#582000
0#
#583000
0'
1#
#584000
0#
#585000
b111 *
1'
1#
#586000
0#
#587000
0'
1#
#588000
0#
#589000
b1000 *
1'
1#
#590000
0#
#591000
0'
1#
#592000
0#
#593000
b1001 *
1'
1#
#594000
0#
#595000
0'
1#
#596000
0#
#597000
b11 +
b0 *
1!
1'
1#
#598000
0#
#599000
0'
1#
#600000
0#
#601000
0!
b1 *
1'
1#
#602000
0#
#603000
0'
1#
#604000
0#
#605000
b10 *
1'
1#
#606000
0#
#607000
0'
1#
#608000
0#
#609000
b11 *
1'
1#
#610000
0#
#611000
0'
1#
#612000
0#
#613000
b100 *
1'
1#
#614000
0#
#615000
0'
1#
#616000
0#
#617000
b101 *
1'
1#
#618000
0#
#619000
0'
1#
#620000
0#
#621000
b110 *
1'
1#
#622000
0#
#623000
0'
1#
#624000
0#
#625000
b111 *
1'
1#
#626000
0#
#627000
0'
1#
#628000
0#
#629000
b1000 *
1'
1#
#630000
0#
#631000
0'
1#
#632000
0#
#633000
b1001 *
1'
1#
#634000
0#
#635000
0'
1#
#636000
0#
#637000
b0 +
b0 *
1!
1'
1#
#638000
0#
#639000
0'
1#
#640000
0#
b0 "
b0 $
b0 )
#641000
0!
b1 *
1'
1#
#642000
0#
#643000
0'
1#
#644000
0#
#645000
b10 *
1'
1#
#646000
0#
#647000
0'
1#
#648000
0#
#649000
b11 *
1'
1#
#650000
0#
#651000
0'
1#
#652000
0#
#653000
b100 *
1'
1#
#654000
0#
#655000
0'
1#
#656000
0#
#657000
b101 *
1'
1#
#658000
0#
#659000
0'
1#
#660000
0#
#661000
b110 *
1'
1#
#662000
0#
#663000
0'
1#
#664000
0#
#665000
b111 *
1'
1#
#666000
0#
#667000
0'
1#
#668000
0#
#669000
b1000 *
1'
1#
#670000
0#
#671000
0'
1#
#672000
0#
#673000
b1001 *
1'
1#
#674000
0#
#675000
0'
1#
#676000
0#
#677000
b1 +
b0 *
1!
1'
1#
#678000
0#
#679000
0'
1#
#680000
0#
#681000
0!
b1 *
1'
1#
#682000
0#
#683000
0'
1#
#684000
0#
#685000
b10 *
1'
1#
#686000
0#
#687000
0'
1#
#688000
0#
#689000
b11 *
1'
1#
#690000
0#
#691000
0'
1#
#692000
0#
#693000
b100 *
1'
1#
#694000
0#
#695000
0'
1#
#696000
0#
#697000
b101 *
1'
1#
#698000
0#
#699000
0'
1#
#700000
0#
#701000
b110 *
1'
1#
#702000
0#
#703000
0'
1#
#704000
0#
#705000
b111 *
1'
1#
#706000
0#
#707000
0'
1#
#708000
0#
#709000
b1000 *
1'
1#
#710000
0#
#711000
0'
1#
#712000
0#
#713000
b1001 *
1'
1#
#714000
0#
#715000
0'
1#
#716000
0#
#717000
b10 +
b0 *
1!
1'
1#
#718000
0#
#719000
0'
1#
#720000
0#
#721000
0!
b1 *
1'
1#
#722000
0#
#723000
0'
1#
#724000
0#
#725000
b10 *
1'
1#
#726000
0#
#727000
0'
1#
#728000
0#
#729000
b11 *
1'
1#
#730000
0#
#731000
0'
1#
#732000
0#
#733000
b100 *
1'
1#
#734000
0#
#735000
0'
1#
#736000
0#
#737000
b101 *
1'
1#
#738000
0#
#739000
0'
1#
#740000
0#
#741000
b110 *
1'
1#
#742000
0#
#743000
0'
1#
#744000
0#
#745000
b111 *
1'
1#
#746000
0#
#747000
0'
1#
#748000
0#
#749000
b1000 *
1'
1#
#750000
0#
#751000
0'
1#
#752000
0#
#753000
b1001 *
1'
1#
#754000
0#
#755000
0'
1#
#756000
0#
#757000
b11 +
b0 *
1!
1'
1#
#758000
0#
#759000
0'
1#
#760000
0#
#761000
0!
b1 *
1'
1#
#762000
0#
#763000
0'
1#
#764000
0#
#765000
b10 *
1'
1#
#766000
0#
#767000
0'
1#
#768000
0#
#769000
b11 *
1'
1#
#770000
0#
#771000
0'
1#
#772000
0#
#773000
b100 *
1'
1#
#774000
0#
#775000
0'
1#
#776000
0#
#777000
b101 *
1'
1#
#778000
0#
#779000
0'
1#
#780000
0#
#781000
b110 *
1'
1#
#782000
0#
#783000
0'
1#
#784000
0#
#785000
b111 *
1'
1#
#786000
0#
#787000
0'
1#
#788000
0#
#789000
b1000 *
1'
1#
#790000
0#
#791000
0'
1#
#792000
0#
#793000
b1001 *
1'
1#
#794000
0#
#795000
0'
1#
#796000
0#
#797000
b0 +
b0 *
1!
1'
1#
#798000
0#
#799000
0'
1#
#800000
0#
b10000000000000000000000000000000 "
b10000000000000000000000000000000 $
b10000000000000000000000000000000 )
#801000
0!
b1 *
1'
1#
#802000
0#
#803000
0'
1#
#804000
0#
#805000
b10 *
1'
1#
#806000
0#
#807000
0'
1#
#808000
0#
#809000
b11 *
1'
1#
#810000
0#
#811000
0'
1#
#812000
0#
#813000
b100 *
1'
1#
#814000
0#
#815000
0'
1#
#816000
0#
#817000
b101 *
1'
1#
#818000
0#
#819000
0'
1#
#820000
0#
#821000
b110 *
1'
1#
#822000
0#
#823000
0'
1#
#824000
0#
#825000
b111 *
1'
1#
#826000
0#
#827000
0'
1#
#828000
0#
#829000
b1000 *
1'
1#
#830000
0#
#831000
0'
1#
#832000
0#
#833000
b1001 *
1'
1#
#834000
0#
#835000
0'
1#
#836000
0#
#837000
b1 +
b0 *
1!
1'
1#
#838000
0#
#839000
0'
1#
#840000
0#
#841000
0!
b1 *
1'
1#
#842000
0#
#843000
0'
1#
#844000
0#
#845000
b10 *
1'
1#
#846000
0#
#847000
0'
1#
#848000
0#
#849000
b11 *
1'
1#
#850000
0#
#851000
0'
1#
#852000
0#
#853000
b100 *
1'
1#
#854000
0#
#855000
0'
1#
#856000
0#
#857000
b101 *
1'
1#
#858000
0#
#859000
0'
1#
#860000
0#
#861000
b110 *
1'
1#
#862000
0#
#863000
0'
1#
#864000
0#
#865000
b111 *
1'
1#
#866000
0#
#867000
0'
1#
#868000
0#
#869000
b1000 *
1'
1#
#870000
0#
#871000
0'
1#
#872000
0#
#873000
b1001 *
1'
1#
#874000
0#
#875000
0'
1#
#876000
0#
#877000
b10 +
b0 *
1!
1'
1#
#878000
0#
#879000
0'
1#
#880000
0#
#881000
0!
b1 *
1'
1#
#882000
0#
#883000
0'
1#
#884000
0#
#885000
b10 *
1'
1#
#886000
0#
#887000
0'
1#
#888000
0#
#889000
b11 *
1'
1#
#890000
0#
#891000
0'
1#
#892000
0#
#893000
b100 *
1'
1#
#894000
0#
#895000
0'
1#
#896000
0#
#897000
b101 *
1'
1#
#898000
0#
#899000
0'
1#
#900000
0#
#901000
b110 *
1'
1#
#902000
0#
#903000
0'
1#
#904000
0#
#905000
b111 *
1'
1#
#906000
0#
#907000
0'
1#
#908000
0#
#909000
b1000 *
1'
1#
#910000
0#
#911000
0'
1#
#912000
0#
#913000
b1001 *
1'
1#
#914000
0#
#915000
0'
1#
#916000
0#
#917000
b11 +
b0 *
1!
1'
1#
#918000
0#
#919000
0'
1#
#920000
0#
#921000
0!
b1 *
1'
1#
#922000
0#
#923000
0'
1#
#924000
0#
#925000
b10 *
1'
1#
#926000
0#
#927000
0'
1#
#928000
0#
#929000
b11 *
1'
1#
#930000
0#
#931000
0'
1#
#932000
0#
#933000
b100 *
1'
1#
#934000
0#
#935000
0'
1#
#936000
0#
#937000
b101 *
1'
1#
#938000
0#
#939000
0'
1#
#940000
0#
#941000
b110 *
1'
1#
#942000
0#
#943000
0'
1#
#944000
0#
#945000
b111 *
1'
1#
#946000
0#
#947000
0'
1#
#948000
0#
#949000
b1000 *
1'
1#
#950000
0#
#951000
0'
1#
#952000
0#
#953000
1!
b1001 *
1'
1#
#954000
0#
#955000
0'
1#
#956000
0#
#957000
b0 +
b0 *
1'
1#
#958000
0#
#959000
0'
1#
#960000
0#
b11000000000000000000000000000000 "
b11000000000000000000000000000000 $
b11000000000000000000000000000000 )
#961000
0!
b1 *
1'
1#
#962000
0#
#963000
0'
1#
#964000
0#
#965000
b10 *
1'
1#
#966000
0#
#967000
0'
1#
#968000
0#
#969000
b11 *
1'
1#
#970000
0#
#971000
0'
1#
#972000
0#
#973000
b100 *
1'
1#
#974000
0#
#975000
0'
1#
#976000
0#
#977000
b101 *
1'
1#
#978000
0#
#979000
0'
1#
#980000
0#
#981000
b110 *
1'
1#
#982000
0#
#983000
0'
1#
#984000
0#
#985000
b111 *
1'
1#
#986000
0#
#987000
0'
1#
#988000
0#
#989000
b1000 *
1'
1#
#990000
0#
#991000
0'
1#
#992000
0#
#993000
b1001 *
1'
1#
#994000
0#
#995000
0'
1#
#996000
0#
#997000
b1 +
b0 *
1!
1'
1#
#998000
0#
#999000
0'
1#
#1000000
0#
#1001000
0!
b1 *
1'
1#
#1002000
0#
#1003000
0'
1#
#1004000
0#
#1005000
b10 *
1'
1#
#1006000
0#
#1007000
0'
1#
#1008000
0#
#1009000
b11 *
1'
1#
#1010000
0#
#1011000
0'
1#
#1012000
0#
#1013000
b100 *
1'
1#
#1014000
0#
#1015000
0'
1#
#1016000
0#
#1017000
b101 *
1'
1#
#1018000
0#
#1019000
0'
1#
#1020000
0#
#1021000
b110 *
1'
1#
#1022000
0#
#1023000
0'
1#
#1024000
0#
#1025000
b111 *
1'
1#
#1026000
0#
#1027000
0'
1#
#1028000
0#
#1029000
b1000 *
1'
1#
#1030000
0#
#1031000
0'
1#
#1032000
0#
#1033000
b1001 *
1'
1#
#1034000
0#
#1035000
0'
1#
#1036000
0#
#1037000
b10 +
b0 *
1!
1'
1#
#1038000
0#
#1039000
0'
1#
#1040000
0#
#1041000
0!
b1 *
1'
1#
#1042000
0#
#1043000
0'
1#
#1044000
0#
#1045000
b10 *
1'
1#
#1046000
0#
#1047000
0'
1#
#1048000
0#
#1049000
b11 *
1'
1#
#1050000
0#
#1051000
0'
1#
#1052000
0#
#1053000
b100 *
1'
1#
#1054000
0#
#1055000
0'
1#
#1056000
0#
#1057000
b101 *
1'
1#
#1058000
0#
#1059000
0'
1#
#1060000
0#
#1061000
b110 *
1'
1#
#1062000
0#
#1063000
0'
1#
#1064000
0#
#1065000
b111 *
1'
1#
#1066000
0#
#1067000
0'
1#
#1068000
0#
#1069000
b1000 *
1'
1#
#1070000
0#
#1071000
0'
1#
#1072000
0#
#1073000
b1001 *
1'
1#
#1074000
0#
#1075000
0'
1#
#1076000
0#
#1077000
b11 +
b0 *
1!
1'
1#
#1078000
0#
#1079000
0'
1#
#1080000
0#
#1081000
0!
b1 *
1'
1#
#1082000
0#
#1083000
0'
1#
#1084000
0#
#1085000
b10 *
1'
1#
#1086000
0#
#1087000
0'
1#
#1088000
0#
#1089000
b11 *
1'
1#
#1090000
0#
#1091000
0'
1#
#1092000
0#
#1093000
b100 *
1'
1#
#1094000
0#
#1095000
0'
1#
#1096000
0#
#1097000
b101 *
1'
1#
#1098000
0#
#1099000
0'
1#
#1100000
0#
#1101000
b110 *
1'
1#
#1102000
0#
#1103000
0'
1#
#1104000
0#
#1105000
b111 *
1'
1#
#1106000
0#
#1107000
0'
1#
#1108000
0#
#1109000
1!
b1000 *
1'
1#
#1110000
0#
#1111000
0'
1#
#1112000
0#
#1113000
b1001 *
1'
1#
#1114000
0#
#1115000
0'
1#
#1116000
0#
#1117000
b0 +
b0 *
1'
1#
#1118000
0#
#1119000
0'
1#
#1120000
0#
b111 "
b111 $
b111 )
